dbt_column_lineage_extractor/__init__.py
dbt_column_lineage_extractor/cli_direct.py
dbt_column_lineage_extractor/cli_recursive.py
dbt_column_lineage_extractor/extractor.py
dbt_column_lineage_extractor/utils.py
dbt_column_lineage_extractor-0.1.1.dist-info/METADATA
dbt_column_lineage_extractor-0.1.1.dist-info/WHEEL
dbt_column_lineage_extractor-0.1.1.dist-info/entry_points.txt
dbt_column_lineage_extractor-0.1.1.dist-info/top_level.txt
dbt_column_lineage_extractor-0.1.1.dist-info/RECORD
