Metadata-Version: 2.1
Name: dbt-column-lineage-extractor
Version: 0.1.1
Summary: A package for extracting dbt column lineage
Home-page: https://github.com/canva-public/dbt-column-lineage-extractor
Author: Wen Wu
Author-email: wenwu@canva.com
Classifier: Programming Language :: Python :: 3
Classifier: License :: OSI Approved :: MIT License
Classifier: Operating System :: OS Independent
Requires-Python: >=3.8
Requires-Dist: sqlglot[rs]==25.24.5
